django_mips-0.2.0.dist-info/pbr.json
django_mips-0.2.0.dist-info/metadata.json
django_mips-0.2.0.dist-info/METADATA
django_mips-0.2.0.dist-info/WHEEL
django_mips-0.2.0.dist-info/RECORD
django_mips-0.2.0.dist-info/DESCRIPTION.rst
django_mips-0.2.0.dist-info/top_level.txt
mips/models.py
mips/tests.pyc
mips/__init__.py
mips/tests.py
mips/dbsettings_production.py
mips/settings.py
mips/views.py
mips/__init__.pyc
mips/models.pyc
mips/dbsettings_default.pyc
mips/views.pyc
mips/settings.pyc
mips/dbsettings_default.py
mips/example/README.md
mips/example/__init__.py
mips/example/examples.py
mips/example/diagram.jpg
mips/example/examples2.py
mips/example/examples.pyc
mips/example/__init__.pyc
mips/example/examples2.pyc
mips/example/example_list.txt
mips/data_manager/__init__.py
mips/data_manager/import_methods.py
mips/data_manager/import_methods.pyc
mips/data_manager/__init__.pyc
mips/data_manager/run_me_to_load_mip_data.py
mips/data_manager/run_me_to_load_mip_data.pyc
mips/data_manager/sample_data/MIP_instance.txt
mips/data_manager/sample_data/MIP_paralogs.txt
mips/data_manager/sample_data/Subspecies.txt
mips/data_manager/sample_data/MIP_samples.txt
mips/data_manager/sample_data/SampleSubspecies.txt
mips/data_manager/sample_data/MIP.txt
