Metadata-Version: 2.0
Name: django-mips
Version: 0.2.0
Summary: A simple API (build on top of the Django Model API) to store and manage MIP (molecular inversion probe) markers.
Home-page: https://github.com/michal-stuglik/django-mips
Author: Michal Stuglik
Author-email: michal@codelabs.info
License: MIT License
Platform: UNKNOWN
Classifier: Environment :: Web Environment
Classifier: Framework :: Django :: 1.7
Classifier: Framework :: Django :: 1.8
Classifier: Intended Audience :: Developers
Classifier: Intended Audience :: Science/Research
Classifier: License :: OSI Approved :: MIT License
Classifier: Operating System :: OS Independent
Classifier: Programming Language :: Python
Classifier: Programming Language :: Python :: 2.7
Classifier: Topic :: Internet :: WWW/HTTP
Classifier: Topic :: Scientific/Engineering :: Bio-Informatics
